README.md
setup.py
headline_gen/Control.py
headline_gen/__init__.py
headline_gen.egg-info/PKG-INFO
headline_gen.egg-info/SOURCES.txt
headline_gen.egg-info/dependency_links.txt
headline_gen.egg-info/requires.txt
headline_gen.egg-info/top_level.txt