Metadata-Version: 2.1
Name: headline-gen
Version: 2.4
Summary: Provides functionality to generate headlines from articles using natural language processing techniques.
Author: venkatchoudharyala
Author-email: venkatchoudhary.ala@gmail.com
Requires-Python: >=3.6
